arrivy
