Metadata-Version: 2.1
Name: arrivy-google-cloud-bigquery
Version: 3.14.4
Summary: Google BigQuery API client library
Home-page: https://github.com/googleapis/python-bigquery
Author: Arrivy
Author-email: support@arrivy.com
License: Apache 2.0
Platform: Posix; MacOS X; Windows
Classifier: Development Status :: 5 - Production/Stable
Classifier: Intended Audience :: Developers
Classifier: License :: OSI Approved :: Apache Software License
Classifier: Programming Language :: Python
Classifier: Programming Language :: Python :: 3
Classifier: Programming Language :: Python :: 3.7
Classifier: Programming Language :: Python :: 3.8
Classifier: Programming Language :: Python :: 3.9
Classifier: Programming Language :: Python :: 3.10
Classifier: Programming Language :: Python :: 3.11
Classifier: Programming Language :: Python :: 3.12
Classifier: Operating System :: OS Independent
Classifier: Topic :: Internet
Requires-Python: >=3.7
License-File: LICENSE
Requires-Dist: google-api-core!=2.0.*,!=2.1.*,!=2.2.*,!=2.3.0,<3.0.0dev,>=1.31.5
Requires-Dist: google-cloud-core<3.0.0dev,>=1.6.0
Requires-Dist: google-resumable-media<3.0dev,>=0.6.0
Requires-Dist: packaging>=20.0.0
Requires-Dist: python-dateutil<3.0dev,>=2.7.2
Requires-Dist: requests<3.0.0dev,>=2.21.0
Provides-Extra: bqstorage
Requires-Dist: google-cloud-bigquery-storage<3.0.0dev,>=2.6.0; extra == "bqstorage"
Requires-Dist: grpcio<2.0dev,>=1.47.0; extra == "bqstorage"
Requires-Dist: grpcio<2.0dev,>=1.49.1; python_version >= "3.11" and extra == "bqstorage"
Requires-Dist: pyarrow>=3.0.0; extra == "bqstorage"
Provides-Extra: pandas
Requires-Dist: pandas>=1.1.0; extra == "pandas"
Requires-Dist: pyarrow>=3.0.0; extra == "pandas"
Requires-Dist: db-dtypes<2.0.0dev,>=0.3.0; extra == "pandas"
Requires-Dist: importlib_metadata>=1.0.0; python_version < "3.8" and extra == "pandas"
Provides-Extra: ipywidgets
Requires-Dist: ipywidgets>=7.7.0; extra == "ipywidgets"
Requires-Dist: ipykernel>=6.0.0; extra == "ipywidgets"
Provides-Extra: geopandas
Requires-Dist: geopandas<1.0dev,>=0.9.0; extra == "geopandas"
Requires-Dist: Shapely<3.0.0dev,>=1.8.4; extra == "geopandas"
Provides-Extra: ipython
Requires-Dist: ipython!=8.1.0,>=7.23.1; extra == "ipython"
Requires-Dist: ipykernel>=6.0.0; extra == "ipython"
Provides-Extra: tqdm
Requires-Dist: tqdm<5.0.0dev,>=4.7.4; extra == "tqdm"
Provides-Extra: opentelemetry
Requires-Dist: opentelemetry-api>=1.1.0; extra == "opentelemetry"
Requires-Dist: opentelemetry-sdk>=1.1.0; extra == "opentelemetry"
Requires-Dist: opentelemetry-instrumentation>=0.20b0; extra == "opentelemetry"
Provides-Extra: bigquery-v2
Requires-Dist: proto-plus<2.0.0dev,>=1.15.0; extra == "bigquery-v2"
Requires-Dist: protobuf!=3.20.0,!=3.20.1,!=4.21.0,!=4.21.1,!=4.21.2,!=4.21.3,!=4.21.4,!=4.21.5,<5.0.0dev,>=3.19.5; extra == "bigquery-v2"
Provides-Extra: all
Requires-Dist: google-cloud-bigquery-storage<3.0.0dev,>=2.6.0; extra == "all"
Requires-Dist: grpcio<2.0dev,>=1.47.0; extra == "all"
Requires-Dist: grpcio<2.0dev,>=1.49.1; python_version >= "3.11" and extra == "all"
Requires-Dist: pyarrow>=3.0.0; extra == "all"
Requires-Dist: pandas>=1.1.0; extra == "all"
Requires-Dist: pyarrow>=3.0.0; extra == "all"
Requires-Dist: db-dtypes<2.0.0dev,>=0.3.0; extra == "all"
Requires-Dist: importlib_metadata>=1.0.0; python_version < "3.8" and extra == "all"
Requires-Dist: ipywidgets>=7.7.0; extra == "all"
Requires-Dist: ipykernel>=6.0.0; extra == "all"
Requires-Dist: geopandas<1.0dev,>=0.9.0; extra == "all"
Requires-Dist: Shapely<3.0.0dev,>=1.8.4; extra == "all"
Requires-Dist: ipython!=8.1.0,>=7.23.1; extra == "all"
Requires-Dist: ipykernel>=6.0.0; extra == "all"
Requires-Dist: tqdm<5.0.0dev,>=4.7.4; extra == "all"
Requires-Dist: opentelemetry-api>=1.1.0; extra == "all"
Requires-Dist: opentelemetry-sdk>=1.1.0; extra == "all"
Requires-Dist: opentelemetry-instrumentation>=0.20b0; extra == "all"
Requires-Dist: proto-plus<2.0.0dev,>=1.15.0; extra == "all"
Requires-Dist: protobuf!=3.20.0,!=3.20.1,!=4.21.0,!=4.21.1,!=4.21.2,!=4.21.3,!=4.21.4,!=4.21.5,<5.0.0dev,>=3.19.5; extra == "all"
